osstatus/__init__.py
osstatus/__main__.py
osstatus/cache.pickle
osstatus/cache.py
osstatus-1.0.5.dist-info/LICENSE
osstatus-1.0.5.dist-info/METADATA
osstatus-1.0.5.dist-info/WHEEL
osstatus-1.0.5.dist-info/entry_points.txt
osstatus-1.0.5.dist-info/top_level.txt
osstatus-1.0.5.dist-info/RECORD
