Metadata-Version: 2.1
Name: osstatus
Version: 1.0.5
Summary: Get os status from the OSStatus website
Author-email: yotam <yotamolenik@gmail.com>
Maintainer-email: yotam <yotamolenik@gmail.com>
License: GNU GENERAL PUBLIC LICENSE
Project-URL: Homepage, https://github.com/yotamolenik/osstatus
Project-URL: Bug Reports, https://github.com/yotamolenik/osstatus/issues
Keywords: ios,error,parser
Classifier: Development Status :: 5 - Production/Stable
Classifier: License :: OSI Approved :: GNU General Public License v3 or later (GPLv3+)
Classifier: Programming Language :: Python :: 3
Classifier: Programming Language :: Python :: 3.8
Classifier: Programming Language :: Python :: 3.9
Classifier: Programming Language :: Python :: 3.10
Classifier: Programming Language :: Python :: 3.11
Classifier: Programming Language :: Python :: 3 :: Only
Requires-Python: >=3.8
License-File: LICENSE
Requires-Dist: click
Requires-Dist: requests
Requires-Dist: bs4
Requires-Dist: beautifulsoup4
Requires-Dist: setuptools
Requires-Dist: pygments
Provides-Extra: test
Requires-Dist: pytest ; extra == 'test'
